aiomagra/__init__.py
aiomagra/accelerometer.proto
aiomagra/accelerometer_pb2.py
aiomagra/addon.proto
aiomagra/addon_pb2.py
aiomagra/admin.proto
aiomagra/admin_pb2.py
aiomagra/battery.proto
aiomagra/battery_pb2.py
aiomagra/ble.proto
aiomagra/ble_pb2.py
aiomagra/bsensor.proto
aiomagra/bsensor_pb2.py
aiomagra/carbon_dioxide.proto
aiomagra/carbon_dioxide_pb2.py
aiomagra/carbon_monoxide.proto
aiomagra/carbon_monoxide_pb2.py
aiomagra/client.py
aiomagra/color.proto
aiomagra/color_pb2.py
aiomagra/configuration.proto
aiomagra/configuration_pb2.py
aiomagra/const.py
aiomagra/devices.proto
aiomagra/devices_pb2.py
aiomagra/door.proto
aiomagra/door_pb2.py
aiomagra/doorbell.proto
aiomagra/doorbell_pb2.py
aiomagra/emergency.proto
aiomagra/emergency_pb2.py
aiomagra/firmware.proto
aiomagra/firmware_pb2.py
aiomagra/flood.proto
aiomagra/flood_pb2.py
aiomagra/gate.proto
aiomagra/gate_pb2.py
aiomagra/gateway.proto
aiomagra/gateway_pb2.py
aiomagra/heartbeat.proto
aiomagra/heartbeat_pb2.py
aiomagra/info.proto
aiomagra/info_pb2.py
aiomagra/level.proto
aiomagra/level_pb2.py
aiomagra/lock.proto
aiomagra/lock_pb2.py
aiomagra/messaging.proto
aiomagra/messaging_pb2.py
aiomagra/metadata.proto
aiomagra/metadata_pb2.py
aiomagra/meter.proto
aiomagra/meter_pb2.py
aiomagra/mqtt.proto
aiomagra/mqtt_pb2.py
aiomagra/power_source.proto
aiomagra/power_source_pb2.py
aiomagra/pubsub.proto
aiomagra/pubsub_pb2.py
aiomagra/remote.proto
aiomagra/remote_pb2.py
aiomagra/reports.proto
aiomagra/reports_pb2.py
aiomagra/roller_shutter.proto
aiomagra/roller_shutter_pb2.py
aiomagra/seismic.proto
aiomagra/seismic_pb2.py
aiomagra/sensor.proto
aiomagra/sensor_pb2.py
aiomagra/siren.proto
aiomagra/siren_pb2.py
aiomagra/smoke.proto
aiomagra/smoke_pb2.py
aiomagra/status.proto
aiomagra/status_pb2.py
aiomagra/structure.proto
aiomagra/structure_pb2.py
aiomagra/switch.proto
aiomagra/switch_pb2.py
aiomagra/tamper.proto
aiomagra/tamper_pb2.py
aiomagra/taptap.proto
aiomagra/taptap_pb2.py
aiomagra/temperature.proto
aiomagra-0.2.0.dist-info/METADATA
aiomagra-0.2.0.dist-info/WHEEL
aiomagra-0.2.0.dist-info/RECORD
